cardtrader/__init__.py
cardtrader/exceptions.py
cardtrader/service.py
cardtrader/sqlite_cache.py
cardtrader/schemas/__init__.py
cardtrader/schemas/blueprint.py
cardtrader/schemas/category.py
cardtrader/schemas/expansion.py
cardtrader/schemas/game.py
cardtrader/schemas/info.py
cardtrader/schemas/product.py
cardtrader_wrapper-0.3.1.dist-info/METADATA
cardtrader_wrapper-0.3.1.dist-info/WHEEL
cardtrader_wrapper-0.3.1.dist-info/licenses/LICENSE.txt
cardtrader_wrapper-0.3.1.dist-info/RECORD
