Metadata-Version: 2.1
Name: CardTrader-Wrapper
Version: 0.3.1
Summary: A Python wrapper for the CardTrader API.
Project-URL: Documentation, https://cardtrader-wrapper.readthedocs.io/en/latest/
Project-URL: Homepage, https://pypi.org/project/CardTrader-Wrapper
Project-URL: Issues, https://github.com/Buried-In-Code/CardTrader-Wrapper/issues
Project-URL: Source, https://github.com/Buried-In-Code/CardTrader-Wrapper
Author-email: BuriedInCode <BuriedInCode@tuta.io>
License-File: LICENSE.txt
Classifier: Development Status :: 4 - Beta
Classifier: Intended Audience :: Developers
Classifier: License :: OSI Approved :: MIT License
Classifier: Natural Language :: English
Classifier: Operating System :: MacOS
Classifier: Operating System :: Microsoft :: Windows
Classifier: Operating System :: POSIX :: Linux
Classifier: Programming Language :: Python :: 3.7
Classifier: Programming Language :: Python :: 3.8
Classifier: Programming Language :: Python :: 3.9
Classifier: Programming Language :: Python :: 3.10
Classifier: Programming Language :: Python :: 3.11
Classifier: Typing :: Typed
Requires-Python: >=3.7
Requires-Dist: pydantic>=1.10.2
Requires-Dist: ratelimit>=2.2.1
Requires-Dist: requests>=2.28.1
Provides-Extra: dev
Requires-Dist: pre-commit>=2.20.0; extra == 'dev'
Provides-Extra: docs
Requires-Dist: mkdocs-include-markdown-plugin>=3.9.1; extra == 'docs'
Requires-Dist: mkdocs>=1.4.1; extra == 'docs'
Requires-Dist: mkdocstrings[python]>=0.19.0; extra == 'docs'
Provides-Extra: test
Requires-Dist: pytest-cov>=4.0.0; extra == 'test'
Requires-Dist: pytest>=7.2.0; extra == 'test'
Requires-Dist: tox-pyenv>=1.1.0; extra == 'test'
Requires-Dist: tox>=3.27.0; extra == 'test'
